LICENSE
MANIFEST.in
README.rst
setup.cfg
setup.py
ansicon/ANSI32.dll
ansicon/ANSI64.dll
ansicon/__init__.py
ansicon.egg-info/PKG-INFO
ansicon.egg-info/SOURCES.txt
ansicon.egg-info/dependency_links.txt
ansicon.egg-info/not-zip-safe
ansicon.egg-info/top_level.txt
tests/__init__.py
tests/__init__.pyc
tests/test_ansicon.py
tests/test_ansicon.pyc
tests/__pycache__/__init__.cpython-37.pyc
tests/__pycache__/test_ansicon.cpython-37.pyc