Metadata-Version: 1.2
Name: ansicon
Version: 1.88.0
Summary: Python wrapper for loading Jason Hood's ANSICON
Home-page: https://github.com/Rockhopper-Technologies/ansicon
Author: Avram Lubkin
Author-email: avylove@rockhopper.net
Maintainer: Avram Lubkin
Maintainer-email: avylove@rockhopper.net
License: MPLv2.0
Keywords: ansicon terminal console
Platform: UNKNOWN
Classifier: Development Status :: 5 - Production/Stable
Classifier: Environment :: Console
Classifier: Intended Audience :: Developers
Classifier: License :: OSI Approved :: Mozilla Public License 2.0 (MPL 2.0)
Classifier: Operating System :: Microsoft :: Windows
Classifier: Programming Language :: Python
Classifier: Programming Language :: Python :: 2.7
Classifier: Programming Language :: Python :: 3.4
Classifier: Programming Language :: Python :: 3.5
Classifier: Programming Language :: Python :: 3.6
Classifier: Programming Language :: Python :: 3.7
Classifier: Programming Language :: Python :: Implementation :: CPython
Classifier: Programming Language :: Python :: Implementation :: PyPy
Classifier: Topic :: Utilities
